LICENSE.txt
MANIFEST.in
README.rst
requirements-py2.txt
requirements-strict.txt
setup.cfg
setup.py
versioneer.py
blaze/__init__.py
blaze/_version.py
blaze/cached.py
blaze/compatibility.py
blaze/dispatch.py
blaze/index.py
blaze/interactive.py
blaze/mongo.py
blaze/partition.py
blaze/sql.py
blaze/utils.py
blaze.egg-info/PKG-INFO
blaze.egg-info/SOURCES.txt
blaze.egg-info/dependency_links.txt
blaze.egg-info/entry_points.txt
blaze.egg-info/requires.txt
blaze.egg-info/top_level.txt
blaze/compute/__init__.py
blaze/compute/bcolz.py
blaze/compute/chunks.py
blaze/compute/core.py
blaze/compute/csv.py
blaze/compute/dask.py
blaze/compute/h5py.py
blaze/compute/hdfstore.py
blaze/compute/json.py
blaze/compute/mongo.py
blaze/compute/numba.py
blaze/compute/numexpr.py
blaze/compute/numpy.py
blaze/compute/pandas.py
blaze/compute/pmap.py
blaze/compute/pydatetime.py
blaze/compute/pyfunc.py
blaze/compute/pytables.py
blaze/compute/python.py
blaze/compute/spark.py
blaze/compute/sparksql.py
blaze/compute/sql.py
blaze/compute/utils.py
blaze/compute/tests/conftest.py
blaze/compute/tests/test_bcolz_compute.py
blaze/compute/tests/test_chunks.py
blaze/compute/tests/test_comprehensive.py
blaze/compute/tests/test_core_compute.py
blaze/compute/tests/test_csv_compute.py
blaze/compute/tests/test_dask.py
blaze/compute/tests/test_dask_dataframe.py
blaze/compute/tests/test_h5py.py
blaze/compute/tests/test_hdfstore.py
blaze/compute/tests/test_json.py
blaze/compute/tests/test_mongo_compute.py
blaze/compute/tests/test_mysql_compute.py
blaze/compute/tests/test_numba.py
blaze/compute/tests/test_numpy_compute.py
blaze/compute/tests/test_optimize_compute.py
blaze/compute/tests/test_pandas_compute.py
blaze/compute/tests/test_pmap.py
blaze/compute/tests/test_postgresql_compute.py
blaze/compute/tests/test_pydatetime.py
blaze/compute/tests/test_pyfunc.py
blaze/compute/tests/test_pytables_compute.py
blaze/compute/tests/test_python_compute.py
blaze/compute/tests/test_spark.py
blaze/compute/tests/test_sparksql.py
blaze/compute/tests/test_sql_compute.py
blaze/compute/tests/test_url_csv_compute.py
blaze/examples/data/accounts-datetimes.csv
blaze/examples/data/accounts-streaming.json
